{
  "productName": "ReversedFront",
  "version": "2.11.1",
  "identifier": "com.reversedfront.app",
  "build": {
    "beforeDevCommand": "",
    "beforeBuildCommand": "",
    "frontendDist": "../assets"
  },
  "bundle": {
    "active": true,
    "category": "DeveloperTool",
    "icon": [
      "icons/32x32.png",
      "icons/128x128.png",
      "icons/128x128@2x.png",
      "icons/icon.icns",
      "icons/icon.ico"
    ],
    "resources": [
      "../assets/mod/js/main.bundle.js",
      "../assets/mod/js/main.bundle.js.LICENSE.txt",
      "../assets/mod/js/706.main.bundle.js",
      "../assets/mod/js/tauri_bridge.js",
      "../assets/mod/data/**/*",
      "../assets/static/**/*",
      "../assets/dexopt/**/*",
      "../assets/tiles/**/*"
    ],
    "targets": "all"
  },
  "app": {
    "windows": [
      {
        "title": "逆統戰：烽火",
        "width": 1280,
        "height": 720,
        "minWidth": 800,
        "minHeight": 600,
        "resizable": true,
        "fullscreen": false
      }
    ],
    "security": {
      "csp": null
    }
  }
}
